time_nlp
