Metadata-Version: 2.1
Name: time-nlp
Version: 1.1.3
Summary: ...
Home-page: http://test.com
Author: test
Author-email: test@gmail.com
License: MIT Licence
Keywords: time,nlp
Platform: any
Classifier: Programming Language :: Python :: 2.6
Classifier: Programming Language :: Python :: 2.7
Classifier: Programming Language :: Python :: 3.6
